pydra/tasks/freesurfer/__init__.py
pydra/tasks/freesurfer/gtmseg.py
pydra/tasks/freesurfer/specs.py
pydra/tasks/freesurfer/tkregister2.py
pydra/tasks/freesurfer/mri/__init__.py
pydra/tasks/freesurfer/mri/aparc2aseg.py
pydra/tasks/freesurfer/mri/binarize.py
pydra/tasks/freesurfer/mri/convert.py
pydra/tasks/freesurfer/mri/coreg.py
pydra/tasks/freesurfer/mri/label2vol.py
pydra/tasks/freesurfer/mri/robust_register.py
pydra/tasks/freesurfer/mri/robust_template.py
pydra/tasks/freesurfer/mri/surf2surf.py
pydra/tasks/freesurfer/mri/vol2vol.py
pydra/tasks/freesurfer/mris/__init__.py
pydra/tasks/freesurfer/mris/anatomical_stats.py
pydra/tasks/freesurfer/mris/ca_label.py
pydra/tasks/freesurfer/mris/ca_train.py
pydra/tasks/freesurfer/mris/expand.py
pydra/tasks/freesurfer/mris/preproc.py
pydra/tasks/freesurfer/recon_all/__init__.py
pydra/tasks/freesurfer/recon_all/base_recon_all.py
pydra/tasks/freesurfer/recon_all/long_recon_all.py
pydra/tasks/freesurfer/recon_all/recon_all.py
pydra/tasks/freesurfer/recon_all/specs.py
pydra/tasks/freesurfer/recon_all/tests/__init__.py
pydra/tasks/freesurfer/recon_all/tests/test_base_recon_all.py
pydra/tasks/freesurfer/recon_all/tests/test_long_recon_all.py
pydra/tasks/freesurfer/recon_all/tests/test_recon_all.py
pydra/tasks/freesurfer/recon_all/tests/test_specs.py
clinica_pydra_freesurfer-0.1.0.dist-info/METADATA
clinica_pydra_freesurfer-0.1.0.dist-info/WHEEL
clinica_pydra_freesurfer-0.1.0.dist-info/licenses/LICENSE
clinica_pydra_freesurfer-0.1.0.dist-info/RECORD
